{"info":{"subdir":"noarch"},"packages":{},"packages.conda":{"pesci-0.1.0-py_0.conda":{"build":"py_0","build_number":0,"depends":["coloredlogs","datatable","matplotlib","networkx","numpy >=2.0","pandas >=2.2.2","python >=3.7,<3.11","scanpy >=1.10.1","scikit-learn >=1.5.2","scipy","seaborn","tqdm"],"legacy_bz2_md5":null,"license":"NONE","license_family":"NONE","md5":"34000a2a03cb0ef34eb4a44adea4d8ef","name":"pesci","noarch":"python","sha256":"7b2a714597a84423dd22ffa931a5b1a921b67e14dec2b0012f8502bb39c1c8d3","size":235878,"subdir":"noarch","timestamp":1761141679650,"version":"0.1.0"}},"removed":[],"repodata_version":1}